LICENSE
MANIFEST.in
README.rst
setup.py
dict2obj/__init__.py
dict2obj/dict2obj.py
dict2obj.egg-info/PKG-INFO
dict2obj.egg-info/SOURCES.txt
dict2obj.egg-info/dependency_links.txt
dict2obj.egg-info/top_level.txt
dict2obj.egg-info/zip-safe