Metadata-Version: 1.1
Name: dict2obj
Version: 1.2.0
Summary: Dict2obj: transform dict to simpler object
Home-page: https://github.com/Senmumu/dict2obj
Author: Ryan Luo
Author-email: luo_senmu@163.com
License: MIT License
Keywords: dict,python,object,data srtucture,transform
Platform: any
Classifier: Development Status :: 5 - Production/Stable
Classifier: Intended Audience :: Developers
Classifier: Natural Language :: English
Classifier: License :: OSI Approved :: MIT License
Classifier: Programming Language :: Python
Classifier: Programming Language :: Python :: 2
Classifier: Programming Language :: Python :: 2.6
Classifier: Programming Language :: Python :: 2.7
Classifier: Programming Language :: Python :: 3
Classifier: Programming Language :: Python :: 3.4
Classifier: Programming Language :: Python :: 3.5
Classifier: Programming Language :: Python :: 3.6
Classifier: Programming Language :: Python :: Implementation :: CPython
